main.py
mseep_mcp_netsuite-0.1.5.dist-info/METADATA
mseep_mcp_netsuite-0.1.5.dist-info/WHEEL
mseep_mcp_netsuite-0.1.5.dist-info/entry_points.txt
mseep_mcp_netsuite-0.1.5.dist-info/top_level.txt
mseep_mcp_netsuite-0.1.5.dist-info/RECORD
